dataherb/__init__.py
dataherb/command.py
dataherb/flora.py
dataherb/version.py
dataherb/cmd/__init__.py
dataherb/cmd/configs.py
dataherb/cmd/create.py
dataherb/cmd/search.py
dataherb/cmd/sync_git.py
dataherb/cmd/sync_s3.py
dataherb/core/__init__.py
dataherb/core/base.py
dataherb/core/search.py
dataherb/fetch/__init__.py
dataherb/fetch/remote.py
dataherb/parse/__init__.py
dataherb/parse/csv.py
dataherb/parse/model_json.py
dataherb/parse/model_yaml.py
dataherb/serve/__init__.py
dataherb/serve/mkdocs_templates.py
dataherb/serve/models.py
dataherb/serve/save_mkdocs.py
dataherb/serve/mkdocs_template/mkdocs.yml
dataherb/serve/mkdocs_template/herbs/index.md
dataherb/serve/mkdocs_template/overrides/home.html
dataherb/serve/mkdocs_template/overrides/main.html
dataherb/serve/mkdocs_template/overrides/partials/datapackage.html
dataherb/serve/mkdocs_template/overrides/partials/metadata.html
dataherb/utils/__init__.py
dataherb/utils/awscli.py
dataherb/utils/configs.py
dataherb/utils/data.py
dataherb-0.1.5.dist-info/LICENSE
dataherb-0.1.5.dist-info/METADATA
dataherb-0.1.5.dist-info/WHEEL
dataherb-0.1.5.dist-info/entry_points.txt
dataherb-0.1.5.dist-info/top_level.txt
dataherb-0.1.5.dist-info/RECORD
