Metadata-Version: 2.1
Name: dataherb
Version: 0.1.5
Summary: Get clean datasets from DataHerb to boost your data science and data analysis projects
Home-page: https://github.com/DataHerb/dataherb-python
Author: Lei Ma
Author-email: hi@leima.is
License: MIT
Platform: UNKNOWN
Requires-Dist: pandas (>=0.23)
Requires-Dist: requests (>=2.22.0)
Requires-Dist: rapidfuzz (>=0.2.2)
Requires-Dist: ruamel.yaml (>=0.16.10)
Requires-Dist: click (>=7.0)
Requires-Dist: inquirer (>=2.6.3)
Requires-Dist: colorama (>=0.4.3)
Requires-Dist: GitPython (>=3.1.0)
Requires-Dist: loguru (>=0.5.3)
Requires-Dist: datapackage (>=1.15.2)
Requires-Dist: awscli (==1.20.13)
Requires-Dist: docutils (<0.16,>=0.10)
Requires-Dist: mkdocs-material (==7.1.8)
Requires-Dist: python-slugify (==5.0.2)
Requires-Dist: mkdocs-macros-plugin (==0.5.12)
Requires-Dist: rich (>=10.7.0)
Provides-Extra: docs
Requires-Dist: sphinx (>=2.4.1) ; extra == 'docs'
Requires-Dist: sphinx-rtd-theme (>=0.4.3) ; extra == 'docs'
